plynx/__init__.py
plynx/_static_templates.py
plynx/base/__init__.py
plynx/base/executor.py
plynx/base/hub.py
plynx/base/resource.py
plynx/bin/__init__.py
plynx/bin/cli.py
plynx/constants/__init__.py
plynx/constants/collections.py
plynx/constants/node_enums.py
plynx/constants/parameter_types.py
plynx/constants/resource_enums.py
plynx/constants/users.py
plynx/constants/validation_enums.py
plynx/constants/web.py
plynx/db/__init__.py
plynx/db/db_object.py
plynx/db/demo_user_manager.py
plynx/db/folder.py
plynx/db/group.py
plynx/db/node.py
plynx/db/node_cache.py
plynx/db/node_cache_manager.py
plynx/db/node_collection_manager.py
plynx/db/run_cancellation_manager.py
plynx/db/test_db_object.py
plynx/db/user.py
plynx/db/validation_error.py
plynx/db/worker_state.py
plynx/demo/__init__.py
plynx/demo/basic_functions.py
plynx/demo/hello_world.py
plynx/demo/types.py
plynx/node/__init__.py
plynx/node/typing.py
plynx/node/utils.py
plynx/plugins/__init__.py
plynx/plugins/argo.py
plynx/plugins/executors/__init__.py
plynx/plugins/executors/bases.py
plynx/plugins/executors/dag.py
plynx/plugins/executors/kubernetes.py
plynx/plugins/executors/local.py
plynx/plugins/executors/python/__init__.py
plynx/plugins/executors/python/dag.py
plynx/plugins/executors/python/local.py
plynx/plugins/hubs/__init__.py
plynx/plugins/hubs/collection.py
plynx/plugins/hubs/static_list.py
plynx/plugins/resources/__init__.py
plynx/plugins/resources/cloud_resources.py
plynx/plugins/resources/common.py
plynx/plugins/resources/python/__init__.py
plynx/plugins/resources/python/common.py
plynx/service/__init__.py
plynx/service/cache.py
plynx/service/execute.py
plynx/service/make_operations_meta.py
plynx/service/messages.py
plynx/service/tcp_utils.py
plynx/service/users.py
plynx/service/worker.py
plynx/service/worker_server.py
plynx/utils/__init__.py
plynx/utils/common.py
plynx/utils/config.py
plynx/utils/content.py
plynx/utils/db_connector.py
plynx/utils/exceptions.py
plynx/utils/executor.py
plynx-1.11.1.dist-info/LICENSE
plynx-1.11.1.dist-info/METADATA
plynx-1.11.1.dist-info/WHEEL
plynx-1.11.1.dist-info/entry_points.txt
plynx-1.11.1.dist-info/top_level.txt
plynx-1.11.1.dist-info/RECORD
